pyqt_checkbox_table_widget/__init__.py
pyqt_checkbox_table_widget/checkBox.py
pyqt_checkbox_table_widget/checkBoxTableWidget.py
pyqt_checkbox_table_widget-0.0.14.dist-info/LICENSE
pyqt_checkbox_table_widget-0.0.14.dist-info/METADATA
pyqt_checkbox_table_widget-0.0.14.dist-info/WHEEL
pyqt_checkbox_table_widget-0.0.14.dist-info/top_level.txt
pyqt_checkbox_table_widget-0.0.14.dist-info/RECORD
