Metadata-Version: 2.1
Name: pyqt-checkbox-table-widget
Version: 0.0.14
Summary: PyQt's QTableWidget which has checkbox as first header item
Home-page: https://github.com/yjg30737/pyqt-checkbox-table-widget.git
Author: Jung Gyu Yoon
Author-email: yjg30737@gmail.com
License: MIT
License-File: LICENSE
Requires-Dist: PyQt5 (>=5.8)
